cider/__init__.py
cider/client.py
cider/client_async.py
cider/exceptions.py
cider/transport_http.py
cider/transport_ws.py
cider/types.py
cider/validators.py
cider_py-0.1.1.dist-info/METADATA
cider_py-0.1.1.dist-info/WHEEL
cider_py-0.1.1.dist-info/licenses/LICENSE
cider_py-0.1.1.dist-info/RECORD
