Metadata-Version: 2.4
Name: Cider.py
Version: 0.1.1
Summary: Python sync/async client for the Cider v2 local API (HTTP + Socket.IO).
Project-URL: Homepage, https://github.com/gabrielzv1233/Cider.py
Project-URL: Issues, https://github.com/gabrielzv1233/Cider.py/issues
Author: Gabrielzv1233
License: MIT License
License-File: LICENSE
Keywords: apple music,audio,cider,rpc,socket.io
Classifier: License :: OSI Approved :: MIT License
Classifier: Operating System :: OS Independent
Classifier: Programming Language :: Python :: 3
Classifier: Programming Language :: Python :: 3 :: Only
Classifier: Programming Language :: Python :: 3.9
Classifier: Programming Language :: Python :: 3.10
Classifier: Programming Language :: Python :: 3.11
Classifier: Programming Language :: Python :: 3.12
Classifier: Typing :: Typed
Requires-Python: >=3.9
Requires-Dist: httpx>=0.27
Requires-Dist: python-socketio[client]>=5.11
Requires-Dist: requests>=2.32
